ask_bedrock/__init__.py
ask_bedrock/main.py
ask_bedrock-0.3.3.dist-info/licenses/LICENSE
ask_bedrock-0.3.3.dist-info/licenses/NOTICE
ask_bedrock-0.3.3.dist-info/METADATA
ask_bedrock-0.3.3.dist-info/WHEEL
ask_bedrock-0.3.3.dist-info/entry_points.txt
ask_bedrock-0.3.3.dist-info/top_level.txt
ask_bedrock-0.3.3.dist-info/RECORD
