Metadata-Version: 2.4
Name: ask-bedrock
Version: 0.3.3
Summary: Converse with your favorite Amazon Bedrock LLM from the command line.
Home-page: https://github.com/awslabs/ask-bedrock
Author-email: Ulrich Hinze <uhinze@amazon.de>, Alexander Günsche <lxg@amazon.de>
Keywords: ask-bedrock,GenAI,Bedrock,AWS
Classifier: Development Status :: 4 - Beta
Classifier: Topic :: Utilities
Requires-Python: >=3.9
License-File: LICENSE
License-File: NOTICE
Requires-Dist: click
Requires-Dist: pyyaml
Requires-Dist: boto3==1.37.38
Requires-Dist: mcp
Provides-Extra: test
Requires-Dist: pytest>=7.0.0; extra == "test"
Requires-Dist: pytest-cov>=4.0.0; extra == "test"
Requires-Dist: mock>=5.0.0; extra == "test"
Dynamic: license-file
